libname/__init__.py
libname/hello.py
hellopkgchris123-0.0.1.dist-info/METADATA
hellopkgchris123-0.0.1.dist-info/WHEEL
hellopkgchris123-0.0.1.dist-info/top_level.txt
hellopkgchris123-0.0.1.dist-info/RECORD
